SQython
