Metadata-Version: 2.1
Name: SQython
Version: 0.0.5
Summary: A SQL wrapper for python.
Home-page: UNKNOWN
Author: Max Paul
Author-email: maxkpaul21@gmail.com
License: UNKNOWN
Platform: UNKNOWN
Classifier: Programming Language :: Python :: 3
Classifier: License :: OSI Approved :: MIT License
Classifier: Operating System :: OS Independent
